VisualizingAndUnderstandingConvolutionalNetworksYiwenKanDongJuanjiShenjingwangluo/README.md
VisualizingAndUnderstandingConvolutionalNetworksYiwenKanDongJuanjiShenjingwangluo/__init__.py
VisualizingAndUnderstandingConvolutionalNetworksYiwenKanDongJuanjiShenjingwangluo/__main__.py
VisualizingAndUnderstandingConvolutionalNetworksYiwenKanDongJuanjiShenjingwangluo/file.pdf
VisualizingAndUnderstandingConvolutionalNetworksYiwenKanDongJuanjiShenjingwangluo/index.html
visualizing_and_understanding_convolutional_networks_yiwen_kan_dong_juanji_shenjingwangluo-2024.3.4.0.dist-info/METADATA
visualizing_and_understanding_convolutional_networks_yiwen_kan_dong_juanji_shenjingwangluo-2024.3.4.0.dist-info/WHEEL
visualizing_and_understanding_convolutional_networks_yiwen_kan_dong_juanji_shenjingwangluo-2024.3.4.0.dist-info/entry_points.txt
visualizing_and_understanding_convolutional_networks_yiwen_kan_dong_juanji_shenjingwangluo-2024.3.4.0.dist-info/top_level.txt
visualizing_and_understanding_convolutional_networks_yiwen_kan_dong_juanji_shenjingwangluo-2024.3.4.0.dist-info/RECORD
